task_agents_mcp/__init__.py
task_agents_mcp/__main__.py
task_agents_mcp/agent_manager.py
task_agents_mcp/resource_manager.py
task_agents_mcp/server.py
task_agents_mcp/session_store.py
task_agents_mcp-4.0.0.dist-info/licenses/LICENSE
task_agents_mcp-4.0.0.dist-info/METADATA
task_agents_mcp-4.0.0.dist-info/WHEEL
task_agents_mcp-4.0.0.dist-info/entry_points.txt
task_agents_mcp-4.0.0.dist-info/top_level.txt
task_agents_mcp-4.0.0.dist-info/RECORD
