Metadata-Version: 2.4
Name: task-agents-mcp
Version: 4.0.0
Summary: Multi-tool MCP server for specialized AI agents - each agent as its own tool
Author: vredrick
License: MIT
Project-URL: Homepage, https://github.com/vredrick/task-agent
Project-URL: Repository, https://github.com/vredrick/task-agent.git
Project-URL: Issues, https://github.com/vredrick/task-agent/issues
Keywords: mcp,ai,agents,claude,llm,fastmcp
Classifier: Development Status :: 4 - Beta
Classifier: Intended Audience :: Developers
Classifier: License :: OSI Approved :: MIT License
Classifier: Programming Language :: Python :: 3
Classifier: Programming Language :: Python :: 3.11
Classifier: Programming Language :: Python :: 3.12
Requires-Python: >=3.11
License-File: LICENSE
Requires-Dist: fastmcp>=2.0.0
Requires-Dist: pyyaml>=6.0.0
Dynamic: license-file
